reposcan/__init__.py
reposcan/reposcan.py
reposcan/exporters/CSVExporter.py
reposcan/exporters/FileExporter.py
reposcan/exporters/XLSXExporter.py
reposcan/exporters/__init__.py
reposcan/helpers/Helper.py
reposcan/helpers/__init__.py
reposcan/models/APIInfo.py
reposcan/models/RepoInfo.py
reposcan/models/__init__.py
reposcan/scanners/CSharpScanner.py
reposcan/scanners/FileScanner.py
reposcan/scanners/JavaScanner.py
reposcan/scanners/PythonScanner.py
reposcan/scanners/__init__.py
tests/__init__.py
tests/actix_rust.py
tests/akka_scala.py
tests/aspnet_csharp.py
tests/blazor_csharp.py
tests/codeigniter_php.py
tests/dancer2_perl.py
tests/django_python.py
tests/echo_go.py
tests/expressjs_javascript.py
tests/fastapi_python.py
tests/flask_python.py
tests/gin_go.py
tests/grails_groovy.py
tests/grails_java.py
tests/happijs_javascript.py
tests/kitura_swift.py
tests/koa_javascript.py
tests/ktor_kotlin.py
tests/laravel_php.py
tests/mojolicious_perl.py
tests/nancy_csharp.py
tests/nerves_elixir.py
tests/net_csharp.py
tests/netjs_javascript.py
tests/nextjs_javascript.py
tests/phoenix_elixir.py
tests/play_scala.py
tests/ratpack_groovy.py
tests/revel_go.py
tests/rocket_rust.py
tests/rubyonrails_ruby.py
tests/shiny_r.py
tests/sinatra_ruby.py
tests/springboot_http_java.py
tests/springboot_kotlin.py
tests/springboot_web_java.py
tests/symfony_php.py
tests/testHelper.py
tests/tornado_python.py
tests/vapor_swift.py
tests/warp_rust.py
tests/zend_php.py
reposcan-0.2.dist-info/METADATA
reposcan-0.2.dist-info/WHEEL
reposcan-0.2.dist-info/top_level.txt
reposcan-0.2.dist-info/RECORD
