Metadata-Version: 2.1
Name: reposcan
Version: 0.2
Summary: A simple example package
Home-page: https://github.com/SingularityDevOps/api-governance
Author: Vincent Chau
Author-email: vincent@singularitydevops.io
Classifier: Programming Language :: Python :: 3
Classifier: License :: OSI Approved :: MIT License
Classifier: Operating System :: OS Independent
Requires-Python: >=3.0,<4.0
Requires-Dist: PyGithub
Requires-Dist: gitpython
Requires-Dist: openpyxl
